wqdebug/__init__.py
wqdebug/common.py
wqdebug/wqdebug.py
wqdebug/offline_log/main_decode_bin_demo.py
wqdebug/offline_log/offline_log.py
wqdebug/offline_log/wquart/__init__.py
wqdebug/offline_log/wquart/btsnoop.py
wqdebug/offline_log/wquart/cli.py
wqdebug/offline_log/wquart/crc.py
wqdebug/offline_log/wquart/decode_new.py
wqdebug/offline_log/wquart/log.py
wqdebug/offline_log/wquart/message_new.py
wqdebug/offline_log/wquart/utility.py
wqdebug/wq_gdb/__init__.py
wqdebug/wq_gdb/gdbinit.py
wqdebug/wq_gdb/tools.json
wqdebug/wq_gdb/wq_gdb.py
wqdebug/wq_gdb/coredump/__init__.py
wqdebug/wq_gdb/coredump/corefile.py
wqdebug/wq_gdb/coredump/dumpfile.py
wqdebug/wq_gdb/coredump/elf32.py
wqdebug/wq_gdb/coredump/riscv_core.py
wqdebug/wq_gdb/coredump/xtensa_core.py
wqdebug/wq_gdb/tools/riscv/windows/riscv32-esp-elf-gdb/share/gdb/python/gdb/FrameDecorator.py
wqdebug/wq_gdb/tools/riscv/windows/riscv32-esp-elf-gdb/share/gdb/python/gdb/FrameIterator.py
wqdebug/wq_gdb/tools/riscv/windows/riscv32-esp-elf-gdb/share/gdb/python/gdb/__init__.py
wqdebug/wq_gdb/tools/riscv/windows/riscv32-esp-elf-gdb/share/gdb/python/gdb/disassembler.py
wqdebug/wq_gdb/tools/riscv/windows/riscv32-esp-elf-gdb/share/gdb/python/gdb/frames.py
wqdebug/wq_gdb/tools/riscv/windows/riscv32-esp-elf-gdb/share/gdb/python/gdb/missing_debug.py
wqdebug/wq_gdb/tools/riscv/windows/riscv32-esp-elf-gdb/share/gdb/python/gdb/printing.py
wqdebug/wq_gdb/tools/riscv/windows/riscv32-esp-elf-gdb/share/gdb/python/gdb/prompt.py
wqdebug/wq_gdb/tools/riscv/windows/riscv32-esp-elf-gdb/share/gdb/python/gdb/styling.py
wqdebug/wq_gdb/tools/riscv/windows/riscv32-esp-elf-gdb/share/gdb/python/gdb/types.py
wqdebug/wq_gdb/tools/riscv/windows/riscv32-esp-elf-gdb/share/gdb/python/gdb/unwinder.py
wqdebug/wq_gdb/tools/riscv/windows/riscv32-esp-elf-gdb/share/gdb/python/gdb/xmethod.py
wqdebug/wq_gdb/tools/riscv/windows/riscv32-esp-elf-gdb/share/gdb/python/gdb/command/__init__.py
wqdebug-1.0.6.dist-info/METADATA
wqdebug-1.0.6.dist-info/WHEEL
wqdebug-1.0.6.dist-info/entry_points.txt
wqdebug-1.0.6.dist-info/top_level.txt
wqdebug-1.0.6.dist-info/RECORD
