Metadata-Version: 2.4
Name: wqdebug
Version: 1.0.6
Summary: wuqi debug tool
Author-email: "deng.weiwei" <deng.weiwei@wuqi-tech.com>
License-Expression: Apache-2.0
Classifier: Development Status :: 4 - Beta
Classifier: Intended Audience :: Developers
Classifier: Natural Language :: English
Classifier: Programming Language :: Python
Classifier: Programming Language :: Python :: 3
Classifier: Programming Language :: Python :: 3.6
Classifier: Programming Language :: Python :: 3.7
Classifier: Programming Language :: Python :: 3.8
Classifier: Programming Language :: Python :: 3.9
Classifier: Programming Language :: Python :: 3.10
Classifier: Programming Language :: Python :: 3 :: Only
Classifier: Programming Language :: Python :: Implementation :: CPython
Requires-Python: >=3.7
Requires-Dist: colorama>=0.4.6
Requires-Dist: pyelftools>=0.32
Requires-Dist: requests>=2.31.0
Requires-Dist: wqgdb>=1.0.2
